sqlantic/__init__.py
sqlantic/core.py
sqlantic/model_manager.py
sqlantic-0.0.7.dist-info/LICENSE
sqlantic-0.0.7.dist-info/METADATA
sqlantic-0.0.7.dist-info/WHEEL
sqlantic-0.0.7.dist-info/top_level.txt
sqlantic-0.0.7.dist-info/RECORD
